Metadata-Version: 1.1
Name: stowaway
Version: 0.0.5
Summary: Stowaway gives simple docker image deployment through vagrant provisioned machines.
Home-page: https://github.com/zbyte64/stowaway/
Author: Jason Kraus
Author-email: zbyte64@gmail.com
License: BSD
Platform: UNKNOWN
Classifier: Programming Language :: Python
Classifier: Development Status :: 3 - Alpha
Classifier: Intended Audience :: Developers
Classifier: License :: Public Domain
Classifier: Operating System :: OS Independent
Classifier: Topic :: Software Development :: Libraries :: Python Modules
